pymult.cpython-38-darwin.so
pymult-0.0.2.dist-info/LICENSE
pymult-0.0.2.dist-info/METADATA
pymult-0.0.2.dist-info/WHEEL
pymult-0.0.2.dist-info/top_level.txt
pymult-0.0.2.dist-info/RECORD
