Metadata-Version: 2.1
Name: pymult
Version: 0.0.2
Summary: An example Python package written in x86-64 assembly.
Home-page: https://github.com/tonybaloney/python-assembly-poc
Author: Anthony Shaw
Author-email: anthonyshaw@apache.org
License: BSD-2-Clause
Platform: UNKNOWN
Classifier: Development Status :: 3 - Alpha
Classifier: Intended Audience :: Developers
Classifier: License :: OSI Approved :: BSD License
Classifier: Operating System :: Unix
Classifier: Operating System :: POSIX
Classifier: Programming Language :: Python
Classifier: Programming Language :: Python :: 3.7
Classifier: Programming Language :: Python :: 3.8
Classifier: Topic :: Utilities
Requires-Python: >=3.7
